epiout/__init__.py
epiout/annotate.py
epiout/annotation_config.py
epiout/autoencoder.py
epiout/dataclasses.py
epiout/dataset.py
epiout/epiout.py
epiout/gene.py
epiout/hic.py
epiout/inject.py
epiout/main.py
epiout/negative_binomial.py
epiout/optimizer.py
epiout/plot.py
epiout/result.py
epiout/sflognorm.py
epiout/utils/__init__.py
epiout/utils/common.py
epiout/utils/genomic_features.py
epiout/utils/io.py
epiout/utils/utils.py
epiout-0.0.1.dist-info/METADATA
epiout-0.0.1.dist-info/WHEEL
epiout-0.0.1.dist-info/entry_points.txt
epiout-0.0.1.dist-info/top_level.txt
epiout-0.0.1.dist-info/RECORD
