Metadata-Version: 2.1
Name: epiout
Version: 0.0.1
Summary: EpiOut: outlier detection for DNA accesibility data.
Home-page: https://github.com/muhammedhasan/epiout
Author: M. Hasan Çelik
Author-email: muhammedhasancelik@gmail.com
License: MIT license
Keywords: genomics,ATAC-seq
Classifier: Natural Language :: English
Classifier: Programming Language :: Python :: 3.7
Classifier: Programming Language :: Python :: 3.8
Classifier: Programming Language :: Python :: 3.9
Requires-Dist: setuptools
Requires-Dist: tqdm
Requires-Dist: pyyaml
Requires-Dist: click
Requires-Dist: numpy <=1.23
Requires-Dist: pooch
Requires-Dist: anndata
Requires-Dist: pandas
Requires-Dist: pyarrow
Requires-Dist: pyranges
Requires-Dist: scipy
Requires-Dist: matplotlib
Requires-Dist: seaborn
Requires-Dist: pysam
Requires-Dist: joblib
Requires-Dist: scikit-learn
Requires-Dist: pyBigWig
Requires-Dist: statsmodels
Requires-Dist: tensorflow
Requires-Dist: tensorflow-probability
